{
	"configurations" : 
	[
		{
			"directories" : 
			[
				{
					"build" : ".",
					"jsonFile" : "directory-.-Debug-f5ebdc15457944623624.json",
					"minimumCMakeVersion" : 
					{
						"string" : "3.16"
					},
					"projectIndex" : 0,
					"source" : ".",
					"targetIndexes" : 
					[
						0,
						1,
						2
					]
				}
			],
			"name" : "Debug",
			"projects" : 
			[
				{
					"directoryIndexes" : 
					[
						0
					],
					"name" : "CarRental",
					"targetIndexes" : 
					[
						0,
						1,
						2
					]
				}
			],
			"targets" : 
			[
				{
					"directoryIndex" : 0,
					"id" : "CarRental::@6890427a1f51a3e7e1df",
					"jsonFile" : "target-CarRental-Debug-f86806174d8ed62bc693.json",
					"name" : "CarRental",
					"projectIndex" : 0
				},
				{
					"directoryIndex" : 0,
					"id" : "CarRental_autogen::@6890427a1f51a3e7e1df",
					"jsonFile" : "target-CarRental_autogen-Debug-767e4fe083a1af4cf836.json",
					"name" : "CarRental_autogen",
					"projectIndex" : 0
				},
				{
					"directoryIndex" : 0,
					"id" : "CarRental_autogen_timestamp_deps::@6890427a1f51a3e7e1df",
					"jsonFile" : "target-CarRental_autogen_timestamp_deps-Debug-ca26ff6d84cdb743c025.json",
					"name" : "CarRental_autogen_timestamp_deps",
					"projectIndex" : 0
				}
			]
		}
	],
	"kind" : "codemodel",
	"paths" : 
	{
		"build" : "/home/vladius/Desktop/apps/CarRENTAL/build",
		"source" : "/home/vladius/Desktop/apps/CarRENTAL"
	},
	"version" : 
	{
		"major" : 2,
		"minor" : 6
	}
}
